{
  "version": "0.3.14-fixed",
  "steps": [
    {
      "tag": "CreateField",
      "model": "Event",
      "field": "startUrl",
      "type": "String",
      "arity": "Required"
    },
    {
      "tag": "CreateField",
      "model": "Event",
      "field": "joinUrl",
      "type": "String",
      "arity": "Required"
    },
    {
      "tag": "CreateField",
      "model": "Event",
      "field": "startTime",
      "type": "DateTime",
      "arity": "Required"
    },
    {
      "tag": "CreateField",
      "model": "Event",
      "field": "duration",
      "type": "Int",
      "arity": "Required"
    }
  ]
}